dictanykey/__init__.py
dictanykey/default_dictanykey.py
dictanykey/dictanykey.py
dictanykey/frozen_dictanykey.py
dictanykey/iterables.py
dictanykey/iterators.py
dictanykey/parent.py
dictanykey/unhashmap.py
dictanykey/utils.py
dictanykey/view_objects.py
dictanykey-0.0.5.dist-info/METADATA
dictanykey-0.0.5.dist-info/WHEEL
dictanykey-0.0.5.dist-info/top_level.txt
dictanykey-0.0.5.dist-info/RECORD
