Metadata-Version: 2.1
Name: dictanykey
Version: 0.0.5
Summary: A dict that can use unhashable keys
Home-page: https://github.com/eddiethedean/dictanykey
Author: Odos Matthews
Author-email: odosmatthews@gmail.com
License: MIT
Classifier: License :: OSI Approved :: MIT License
Classifier: Programming Language :: Python :: 3
Classifier: Programming Language :: Python :: 3.6
Classifier: Programming Language :: Python :: 3.7
Classifier: Programming Language :: Python :: 3.8
Requires-Python: >=3.6
